ez_setup.py
pyedra/__init__.py
pyedra/core.py
pyedra/hg1g2_model.py
pyedra/hg_model.py
pyedra/shevchenko_model.py
pyedra/datasets/__init__.py
pyedra/datasets/carbognani2019.csv
pyedra/datasets/gaia.csv.bz2
pyedra/datasets/penttila2016.csv
pyedra/lib/python3.11/site-packages/matplotlib/mpl-data/sample_data/Stocks.csv
pyedra/lib/python3.11/site-packages/matplotlib/mpl-data/sample_data/data_x_x2_x3.csv
pyedra/lib/python3.11/site-packages/matplotlib/mpl-data/sample_data/msft.csv
pyedra/lib/python3.11/site-packages/numpy/_core/tests/data/umath-validation-set-arccos.csv
pyedra/lib/python3.11/site-packages/numpy/_core/tests/data/umath-validation-set-arccosh.csv
pyedra/lib/python3.11/site-packages/numpy/_core/tests/data/umath-validation-set-arcsin.csv
pyedra/lib/python3.11/site-packages/numpy/_core/tests/data/umath-validation-set-arcsinh.csv
pyedra/lib/python3.11/site-packages/numpy/_core/tests/data/umath-validation-set-arctan.csv
pyedra/lib/python3.11/site-packages/numpy/_core/tests/data/umath-validation-set-arctanh.csv
pyedra/lib/python3.11/site-packages/numpy/_core/tests/data/umath-validation-set-cbrt.csv
pyedra/lib/python3.11/site-packages/numpy/_core/tests/data/umath-validation-set-cos.csv
pyedra/lib/python3.11/site-packages/numpy/_core/tests/data/umath-validation-set-cosh.csv
pyedra/lib/python3.11/site-packages/numpy/_core/tests/data/umath-validation-set-exp.csv
pyedra/lib/python3.11/site-packages/numpy/_core/tests/data/umath-validation-set-exp2.csv
pyedra/lib/python3.11/site-packages/numpy/_core/tests/data/umath-validation-set-expm1.csv
pyedra/lib/python3.11/site-packages/numpy/_core/tests/data/umath-validation-set-log.csv
pyedra/lib/python3.11/site-packages/numpy/_core/tests/data/umath-validation-set-log10.csv
pyedra/lib/python3.11/site-packages/numpy/_core/tests/data/umath-validation-set-log1p.csv
pyedra/lib/python3.11/site-packages/numpy/_core/tests/data/umath-validation-set-log2.csv
Pyedra-0.3.2.dist-info/LICENSE
Pyedra-0.3.2.dist-info/METADATA
Pyedra-0.3.2.dist-info/WHEEL
Pyedra-0.3.2.dist-info/top_level.txt
Pyedra-0.3.2.dist-info/RECORD
