Metadata-Version: 2.1
Name: Pyedra
Version: 0.3.2
Summary: Implementation of phase function for asteroids in Python
Home-page: https://github.com/milicolazo/Pyedra
Author: Milagros Colazo
Author-email: milirita.colazovinovo@gmail.com
License: The MIT License
Keywords: pyedra,asteroid,phase function
Classifier: Development Status :: 4 - Beta
Classifier: Intended Audience :: Education
Classifier: Intended Audience :: Science/Research
Classifier: License :: OSI Approved :: MIT License
Classifier: Operating System :: OS Independent
Classifier: Programming Language :: Python
Classifier: Programming Language :: Python :: 3.8
Classifier: Programming Language :: Python :: Implementation :: CPython
Classifier: Topic :: Scientific/Engineering
License-File: LICENSE
Requires-Dist: attrs>=25.0.0
Requires-Dist: matplotlib<4.0,>=3.7.0
Requires-Dist: numpy<2.0,>=1.24.0
Requires-Dist: pandas<3.0,>=2.0.0
Requires-Dist: scipy<2.0,>=1.10.0
